{
  "info": {
    "_postman_id": "034da12f-52fd-4254-9a25-cffbb911c0b9",
    "name": "Backend Assignment API",
    "schema": "https://schema.getpostman.com/json/collection/v2.1.0/collection.json",
    "_exporter_id": "52983672",
    "_collection_link": "https://go.postman.co/collection/52983672-034da12f-52fd-4254-9a25-cffbb911c0b9?source=collection_link"
  },
  "item": [
    {
      "name": "New Request",
      "request": {
        "method": "POST",
        "header": [],
        "body": {
          "mode": "raw",
          "raw": "{\r\n\"name\":\"anuj\",\r\n\"email\":\"anuj@test.com\",\r\n\"password\":\"123\"\r\n}",
          "options": {
            "raw": {
              "language": "json"
            }
          }
        },
        "url": {
          "raw": "http://localhost:5000/api/v1/auth/register",
          "protocol": "http",
          "host": [
            "localhost"
          ],
          "port": "5000",
          "path": [
            "api",
            "v1",
            "auth",
            "register"
          ]
        }
      },
      "response": []
    },
    {
      "name": "New Request",
      "request": {
        "method": "POST",
        "header": [],
        "body": {
          "mode": "raw",
          "raw": "{\r\n\"name\":\"Shubham\",\r\n\"email\":\"test@test.com\",\r\n\"password\":\"123456\"\r\n}",
          "options": {
            "raw": {
              "language": "json"
            }
          }
        },
        "url": {
          "raw": "http://localhost:5000/api/v1/auth/login",
          "protocol": "http",
          "host": [
            "localhost"
          ],
          "port": "5000",
          "path": [
            "api",
            "v1",
            "auth",
            "login"
          ]
        }
      },
      "response": []
    },
    {
      "name": "New Request",
      "request": {
        "auth": {
          "type": "bearer",
          "bearer": [
            {
              "key": "token",
              "value": "eyJhbGciOiJIUzI1NiIsInR5cCI6IkpXVCJ9.eyJpZCI6IjY5YjU0YTNjMGI1YWVhNGViY2UxOGRmZCIsInJvbGUiOiJ1c2VyIiwiaWF0IjoxNzczNDg5ODA3LCJleHAiOjE3NzM1NzYyMDd9.rVyA6N2DCTwRG8r-lCi76OhvFDV3taoNAqb_Sqdxql4",
              "type": "string"
            }
          ]
        },
        "method": "POST",
        "header": [],
        "body": {
          "mode": "raw",
          "raw": "{\r\n\"title\":\"Finish Assignment\",\r\n\"description\":\"Backend task\"\r\n}",
          "options": {
            "raw": {
              "language": "json"
            }
          }
        },
        "url": {
          "raw": "http://localhost:5000/api/v1/tasks",
          "protocol": "http",
          "host": [
            "localhost"
          ],
          "port": "5000",
          "path": [
            "api",
            "v1",
            "tasks"
          ]
        }
      },
      "response": []
    }
  ]
}